setup.py
distributions/Binomialdistribution.py
distributions/Gaussiandistribution.py
distributions/Generaldistribution.py
distributions/__init__.py
dkaqn_distributions.egg-info/PKG-INFO
dkaqn_distributions.egg-info/SOURCES.txt
dkaqn_distributions.egg-info/dependency_links.txt
dkaqn_distributions.egg-info/not-zip-safe
dkaqn_distributions.egg-info/top_level.txt